zvc/__init__.py
zvc/__main__.py
zvc/cli.py
zvc/config.py
zvc-0.1.7.dist-info/METADATA
zvc-0.1.7.dist-info/WHEEL
zvc-0.1.7.dist-info/entry_points.txt
zvc-0.1.7.dist-info/top_level.txt
zvc-0.1.7.dist-info/RECORD
