Metadata-Version: 2.4
Name: zvc
Version: 0.1.7
Summary: static blog generator
Requires-Python: >=3.12
Requires-Dist: markdown>=3.8.2
Requires-Dist: typer>=0.16.0
Requires-Dist: ruff>=0.12.2
Requires-Dist: jinja2>=3.1.6
Requires-Dist: pyyaml>=6.0.2
Requires-Dist: rich>=13.7.1
Requires-Dist: pydantic>=2.11.7
Requires-Dist: beautifulsoup4>=4.13.4
Requires-Dist: lxml>=6.0.0
Provides-Extra: dev
Requires-Dist: pytest>=8.4.1; extra == "dev"
Requires-Dist: pytest-sugar>=1.0.0; extra == "dev"
Requires-Dist: ruff>=0.12.2; extra == "dev"
